{
  "project_info": {
    "project_number": "30443732459",
    "project_id": "zomatoapp-f5756",
    "storage_bucket": "zomatoapp-f5756.appspot.com"
  },
  "client": [
    {
      "client_info": {
        "mobilesdk_app_id": "1:30443732459:android:f98ba26a51a6751e9aedae",
        "android_client_info": {
          "package_name": "com.example.food_app"
        }
      },
      "oauth_client": [
        {
          "client_id": "30443732459-uibirf0mtc7a6mohthrln30petq5bgem.apps.googleusercontent.com",
          "client_type": 3
        }
      ],
      "api_key": [
        {
          "current_key": "AIzaSyBjor5T5R4fam_lJZ4WiiZBbbgpywaCS3M"
        }
      ],
      "services": {
        "appinvite_service": {
          "other_platform_oauth_client": [
            {
              "client_id": "30443732459-uibirf0mtc7a6mohthrln30petq5bgem.apps.googleusercontent.com",
              "client_type": 3
            }
          ]
        }
      }
    },
    {
      "client_info": {
        "mobilesdk_app_id": "1:30443732459:android:0f7a1112a4a674e39aedae",
        "android_client_info": {
          "package_name": "com.example.food_flutter_application"
        }
      },
      "oauth_client": [
        {
          "client_id": "30443732459-uibirf0mtc7a6mohthrln30petq5bgem.apps.googleusercontent.com",
          "client_type": 3
        }
      ],
      "api_key": [
        {
          "current_key": "AIzaSyBjor5T5R4fam_lJZ4WiiZBbbgpywaCS3M"
        }
      ],
      "services": {
        "appinvite_service": {
          "other_platform_oauth_client": [
            {
              "client_id": "30443732459-uibirf0mtc7a6mohthrln30petq5bgem.apps.googleusercontent.com",
              "client_type": 3
            }
          ]
        }
      }
    }
  ],
  "configuration_version": "1"
}